{
  "key": "plugin_content_manager_configuration_content_types::api::home.home",
  "value": {
    "settings": {
      "bulkable": true,
      "filterable": true,
      "searchable": true,
      "pageSize": 10,
      "mainField": "id",
      "defaultSortBy": "id",
      "defaultSortOrder": "ASC"
    },
    "metadatas": {
      "id": {
        "edit": {},
        "list": {
          "label": "id",
          "searchable": true,
          "sortable": true
        }
      },
      "bio": {
        "edit": {
          "label": "bio",
          "description": "",
          "placeholder": "",
          "visible": true,
          "editable": true
        },
        "list": {
          "label": "bio",
          "searchable": true,
          "sortable": true
        }
      },
      "banner": {
        "edit": {
          "label": "banner",
          "description": "",
          "placeholder": "",
          "visible": true,
          "editable": true
        },
        "list": {
          "label": "banner",
          "searchable": false,
          "sortable": false
        }
      },
      "links": {
        "edit": {
          "label": "links",
          "description": "",
          "placeholder": "",
          "visible": true,
          "editable": true
        },
        "list": {
          "label": "links",
          "searchable": false,
          "sortable": false
        }
      },
      "message": {
        "edit": {
          "label": "message",
          "description": "",
          "placeholder": "",
          "visible": true,
          "editable": true
        },
        "list": {
          "label": "message",
          "searchable": true,
          "sortable": true
        }
      },
      "createdAt": {
        "edit": {
          "label": "createdAt",
          "description": "",
          "placeholder": "",
          "visible": false,
          "editable": true
        },
        "list": {
          "label": "createdAt",
          "searchable": true,
          "sortable": true
        }
      },
      "updatedAt": {
        "edit": {
          "label": "updatedAt",
          "description": "",
          "placeholder": "",
          "visible": false,
          "editable": true
        },
        "list": {
          "label": "updatedAt",
          "searchable": true,
          "sortable": true
        }
      },
      "createdBy": {
        "edit": {
          "label": "createdBy",
          "description": "",
          "placeholder": "",
          "visible": false,
          "editable": true,
          "mainField": "firstname"
        },
        "list": {
          "label": "createdBy",
          "searchable": true,
          "sortable": true
        }
      },
      "updatedBy": {
        "edit": {
          "label": "updatedBy",
          "description": "",
          "placeholder": "",
          "visible": false,
          "editable": true,
          "mainField": "firstname"
        },
        "list": {
          "label": "updatedBy",
          "searchable": true,
          "sortable": true
        }
      }
    },
    "layouts": {
      "list": [
        "id",
        "bio",
        "banner",
        "links"
      ],
      "edit": [
        [
          {
            "name": "bio",
            "size": 6
          },
          {
            "name": "banner",
            "size": 6
          }
        ],
        [
          {
            "name": "links",
            "size": 12
          }
        ],
        [
          {
            "name": "message",
            "size": 6
          }
        ]
      ]
    },
    "uid": "api::home.home"
  },
  "type": "object",
  "environment": null,
  "tag": null
}